category/__init__.py
category/admin.py
category/models.py
category/tools.py
category/migrations/0001_initial.py
category/migrations/0001_initial.pyc
category/migrations/0002_auto_20190103_0846.py
category/migrations/__init__.py
category/migrations/__init__.pyc
category/migrations/__pycache__/0001_initial.cpython-36.pyc
category/migrations/__pycache__/0001_initial.cpython-37.pyc
category/migrations/__pycache__/0002_auto_20190103_0846.cpython-36.pyc
category/migrations/__pycache__/__init__.cpython-36.pyc
category/migrations/__pycache__/__init__.cpython-37.pyc
category/south_migrations/0001_initial.py
category/south_migrations/0002_auto__add_field_category_parent.py
category/south_migrations/0003_auto__add_field_category_subtitle.py
category/south_migrations/__init__.py
category/templates/admin/category/tree.html
category/templates/admin/category/tree_node.html
category/tests/__init__.py
category/tests/__init__.pyc
category/tests/test_base.py
category/tests/test_base.pyc
category/tests/__pycache__/__init__.cpython-36.pyc
category/tests/__pycache__/__init__.cpython-37.pyc
category/tests/__pycache__/test_base.cpython-36.pyc
category/tests/__pycache__/test_base.cpython-37.pyc
category/tests/requirements/111.txt
category/tests/requirements/20.txt
category/tests/requirements/21.txt
category/tests/settings/111.py
category/tests/settings/111.pyc
category/tests/settings/20.py
category/tests/settings/21.py
category/tests/settings/__init__.py
category/tests/settings/__init__.pyc
category/tests/settings/__pycache__/111.cpython-36.pyc
category/tests/settings/__pycache__/20.cpython-36.pyc
category/tests/settings/__pycache__/21.cpython-36.pyc
category/tests/settings/__pycache__/21.cpython-37.pyc
category/tests/settings/__pycache__/__init__.cpython-36.pyc
category/tests/settings/__pycache__/__init__.cpython-37.pyc
django_category-2.0.1.dist-info/DESCRIPTION.rst
django_category-2.0.1.dist-info/METADATA
django_category-2.0.1.dist-info/RECORD
django_category-2.0.1.dist-info/WHEEL
django_category-2.0.1.dist-info/metadata.json
django_category-2.0.1.dist-info/top_level.txt
